sheet2api/__init__.py
sheet2api/client.py
sheet2api-0.1.3.dist-info/LICENSE
sheet2api-0.1.3.dist-info/METADATA
sheet2api-0.1.3.dist-info/WHEEL
sheet2api-0.1.3.dist-info/top_level.txt
sheet2api-0.1.3.dist-info/RECORD
