Metadata-Version: 2.1
Name: sheet2api
Version: 0.1.3
Summary: Google/Excel Sheets API Python.
Home-page: https://github.com/ODwyerSoftware/sheet2api-python
Author: Richard O'Dwyer
Author-email: sheet2api@heavyindustries.eu
License: Apache 2.0
Platform: UNKNOWN
Classifier: Intended Audience :: Developers
Classifier: Operating System :: OS Independent
Classifier: Programming Language :: Python
Classifier: Programming Language :: Python :: 3
Classifier: Topic :: Internet :: WWW/HTTP
Requires-Dist: requests (<3.0.0,>=2.0.0)
